start_watching_sites/__init__.py
start_watching_sites/database/__init__.py
start_watching_sites/database/database.py
start_watching_sites/database/models/__init__.py
start_watching_sites/database/models/models.py
start_watching_sites/functions/__init__.py
start_watching_sites/functions/datacheck.py
start_watching_sites/functions/exceltools.py
start_watching_sites/functions/recon.py
start_watching_sites/functions/sitecheck.py
start_watching_sites/main.py
start_watching_sites-0.1.1.dist-info/entry_points.txt
start_watching_sites-0.1.1.dist-info/METADATA
start_watching_sites-0.1.1.dist-info/WHEEL
start_watching_sites-0.1.1.dist-info/RECORD
